huspacy/__init__.py
huspacy/components/__init__.py
huspacy/components/edit_tree_lemmatizer.py
huspacy/components/lemma_postprocessing.py
huspacy/components/lookup_lemmatizer.py
huspacy/extra/__init__.py
huspacy/extra/roman_num_converter.py
huspacy/extra/sentencizer.py
huspacy/integrations/__init__.py
huspacy/integrations/nerpp.py
huspacy/integrations/sentiment.py
huspacy/resources/poltext_sentiment.json
huspacy/resources/precognox_sentiment.json
huspacy/utils.py
huspacy-0.12.1.dist-info/METADATA
huspacy-0.12.1.dist-info/WHEEL
huspacy-0.12.1.dist-info/RECORD
