Metadata-Version: 2.1
Name: huspacy
Version: 0.12.1
Summary: HuSpaCy: industrial strength Hungarian natural language processing
Home-page: https://github.com/huspacy/huspacy
License: Apache-2.0
Keywords: nlp,huspacy,Hungarian,text processing,text processing,language processing,text mining,tokenization,sentence boundary detection,sbd,sentence splitting,pos tagging,tagging,lemmatization,ner,named entity recognition,parsing,word embeddings,word vectors,spacy,spacy model
Author: SzegedAI, MILAB
Author-email: gyorgy@orosz.link
Maintainer: György Orosz
Maintainer-email: gyorgy@orosz.link
Requires-Python: >=3.9,<3.14
Classifier: Development Status :: 3 - Alpha
Classifier: Intended Audience :: Developers
Classifier: Intended Audience :: Science/Research
Classifier: License :: OSI Approved :: Apache Software License
Classifier: Operating System :: OS Independent
Classifier: Programming Language :: Python :: 3
Classifier: Programming Language :: Python :: 3.9
Classifier: Programming Language :: Python :: 3.10
Classifier: Programming Language :: Python :: 3.11
Classifier: Programming Language :: Python :: 3.12
Classifier: Programming Language :: Python :: 3.13
Classifier: Topic :: Scientific/Engineering
Classifier: Topic :: Scientific/Engineering :: Artificial Intelligence
Classifier: Topic :: Scientific/Engineering :: Human Machine Interfaces
Classifier: Topic :: Scientific/Engineering :: Information Analysis
Classifier: Topic :: Text Processing
Classifier: Topic :: Text Processing :: Linguistic
Provides-Extra: morph
Provides-Extra: np
Provides-Extra: trf
Requires-Dist: benepar (==0.2.0) ; extra == "np"
Requires-Dist: packaging (>=21.3,<22.0)
Requires-Dist: spacy-alignments (>=0.8.6,<0.9.0) ; extra == "trf"
Requires-Dist: torch ; extra == "trf"
Requires-Dist: transformers (>=4.24.0,<5.0.0) ; extra == "trf"
Project-URL: Repository, https://github.com/huspacy/huspacy
